{
    "info": {
        "url_png_icon_64x64": "https://github.com/reignxx/m/blob/master/halostakeclean_small.png",
        "url_png_logo": "https://github.com/reignxx/m/blob/master/halostakeclean_64px.png",
        "location": "Omaha, Nebraska",
        "social": {
            "twitter_handle": "",
            "telegram_handle": "HALOSTAKEPOOL",
            "facebook_handle": "",
            "youtube_handle": "",
            "twitch_handle": "",
            "discord_handle": "",
            "github_handle": ""
        },
        "company": {
            "name": "",
            "addr": "",
            "city": "",
            "country": "",
            "company_id": "",
            "vat_id": ""
        },
        "about": {
            "me": "",
            "server": "Raspberry Pi Cluster Hosted on dedicated connection.",
            "company": ""
        }
    },
    "my-pool-ids": {
        "0": "96155e7994343ae2b5da83d895cbab3c21838f95c3f971c8e20ee3c8"
    },
    "when-satured-then-recommend": {
        "0": ""
    },
    "telegram-admin-handle": {
        "0": ""
    }
}
